score.asyncio-0.3.0-py3.7-nspkg.pth
score/asyncio/__init__.py
score/asyncio/_init.py
score/asyncio/worker.py
score.asyncio-0.3.0.dist-info/METADATA
score.asyncio-0.3.0.dist-info/WHEEL
score.asyncio-0.3.0.dist-info/namespace_packages.txt
score.asyncio-0.3.0.dist-info/top_level.txt
score.asyncio-0.3.0.dist-info/RECORD
